vercel_blob/__init__.py
vercel_blob/blob_store.py
vercel_blob/errors.py
vercel_blob/progress.py
vercel_blob/utils.py
vercel_blob-0.4.1.dist-info/LICENSE
vercel_blob-0.4.1.dist-info/METADATA
vercel_blob-0.4.1.dist-info/WHEEL
vercel_blob-0.4.1.dist-info/RECORD
