Metadata-Version: 2.3
Name: vercel_blob
Version: 0.4.1
Summary: A Python Wrapper for Vercel Blob Storage API
Author: SuryaSekhar14
Author-email: suryasekhardatta22@gmail.com
Requires-Python: >=3.10,<4.0
Classifier: Programming Language :: Python :: 3
Classifier: Programming Language :: Python :: 3.10
Classifier: Programming Language :: Python :: 3.11
Classifier: Programming Language :: Python :: 3.12
Classifier: Programming Language :: Python :: 3.13
Requires-Dist: certifi (>=2024.07.04)
Requires-Dist: requests (>=2.32.3,<3.0.0)
Requires-Dist: tqdm (>=4.67.1,<5.0.0)
Requires-Dist: urllib3 (>=2.2.2)
Project-URL: Repository, https://github.com/SuryaSekhar14/vercel_blob
